car_price_predictor/__init__.py
car_price_predictor/data_processing.py
car_price_predictor/model_prediction.py
car_price_predictor/model_training.py
car_price_predictor-0.1.2.dist-info/METADATA
car_price_predictor-0.1.2.dist-info/WHEEL
car_price_predictor-0.1.2.dist-info/top_level.txt
car_price_predictor-0.1.2.dist-info/RECORD
